Workbook

Sheet Summary
A1: Mobile proxy benchmark, 2026-10-24 08:00 .. 2026-10-27 21:16 UTC. Pooled over three test servers (USA, Germany, Singapore). Rates with 95% Wilson confidence interval. Per-server values in the other tabs.
A3: Provider | B3: Success Rate | C3: Latency median / P90, s | D3: Unique IPs | E3: Duplicate Rate | F3: Geo Accuracy | G3: IPv6 share | H3: Weakest Country | I3: Google Success Rate | J3: Instagram Success Rate | K3: Sticky: median IP lifetime, min | L3: Sticky: lived 30 min | M3: Fingerprint: Windows share | N3: Fingerprint: Ethernet MTU 1500 | O3: Fraud Score avg / high risk | P3: Proxy flags (Scamalytics) | Q3: Mobile IP Share | R3: Cost per 1,000 successful, $ | S3: Price, $/GB | T3: Minimum purchase
A4: Floppydata | B4: 98.6% (98.4-98.7) | C4: 1.11 / 2.42 | D4: 23743 of 28393 | E4: 0.16377276 | F4: 99.9% (99.8-99.9) | G4: 0.50058113 | H4: ES 98.2% | I4: 97.8% (97.4-98.1) | J4: 97.1% (96.3-97.8) | K4: 8 | L4: 27.6% (23.4-32.3) (n=384) | M4: 0.2% (0.1-0.5) | N4: 22.9% (20.8-25.0) | O4: 3.5 / 0.7% (0.2-2.4) | P4: 0.0% (0.0-1.3) | Q4: IP2Location 95.1% (94.6-95.5) / MaxMind 88.7% (86.6-90.5) | R4: ='Cost'!H6 | S4: 1 | T4: 19 GB for $19
A5: Byteful | B5: 99.7% (99.6-99.7) | C5: 0.73 / 1.30 | D5: 19989 of 28704 | E5: 0.30361622 | F5: 100.0% (99.9-100.0) | G5: 0.006166388 | H5: IN 99.2% | I5: 95.5% (94.9-96.0) | J5: 99.2% (98.7-99.5) | K5: 30 | L5: 56.5% (51.5-61.4) (n=384) | M5: 49.3% (47.4-51.1) | N5: 29.3% (27.1-31.6) | O5: 3.6 / 1.0% (0.3-2.9) | P5: 0.0% (0.0-1.3) | Q5: IP2Location 98.7% (98.4-98.9) / MaxMind 97.2% (96.0-98.1) | R5: ='Cost'!H7 | S5: 4.25 | T5: 2 GB for $8.50, subscription
A6: DataImpulse | B6: 99.3% (99.2-99.4) | C6: 0.94 / 2.92 | D6: 14507 of 28610 | E6: 0.49293953 | F6: 93.1% (92.8-93.4) | G6: 0.076406851 | H6: VN 97.0% | I6: 91.1% (90.3-91.8) | J6: 98.2% (97.6-98.7) | K6: 30 | L6: 72.4% (67.7-76.6) (n=384) | M6: 11.6% (10.4-12.8) | N6: 41.2% (38.9-43.6) | O6: 4.0 / 1.3% (0.5-3.4) | P6: 0.0% (0.0-1.3) | Q6: IP2Location 90.6% (90.0-91.2) / MaxMind 80.5% (77.9-82.8) | R6: ='Cost'!H8 | S6: 2 | T6: 2.5 GB for $5, one-time (new users)
A7: Decodo | B7: 99.8% (99.7-99.9) | C7: 0.91 / 1.63 | D7: 23323 of 28744 | E7: 0.18859588 | F7: 99.9% (99.9-100.0) | G7: 0.11703312 | H7: IN 99.6% | I7: 96.8% (96.3-97.2) | J7: 99.4% (98.9-99.6) | K7: 30 | L7: 78.6% (74.3-82.5) (n=384) | M7: 24.5% (22.9-26.1) | N7: 37.7% (35.9-39.7) | O7: 2.7 / 0.3% (0.1-1.9) | P7: 0.0% (0.0-1.3) | Q7: IP2Location 96.2% (95.8-96.6) / MaxMind 16.0% (13.9-18.4) | R7: ='Cost'!H9 | S7: 3.75 | T7: 2 GB for $7.50, subscription
A8: Evomi | B8: 98.7% (98.5-98.8) | C8: 0.88 / 1.71 | D8: 18270 of 28415 | E8: 0.35702974 | F8: 99.8% (99.7-99.8) | G8: 0.00073904628 | H8: IN 98.2% | I8: 93.1% (92.4-93.7) | J8: 98.7% (98.1-99.1) | K8: 30 | L8: 54.4% (49.4-59.3) (n=384) | M8: 18.0% (16.6-19.5) | N8: 22.6% (20.6-24.7) | O8: 2.7 / 0.0% (0.0-1.3) | P8: 0.0% (0.0-1.3) | Q8: IP2Location 99.3% (99.1-99.4) / MaxMind 98.7% (97.8-99.2) | R8: ='Cost'!H10 | S8: 3.98 | T8: 4 GB for $15.92, one-time
A9: IPRoyal | B9: 98.8% (98.7-98.9) | C9: 1.25 / 3.35 | D9: 24661 of 28462 | E9: 0.13354648 | F9: 100.0% (100.0-100.0) | G9: 0.010294428 | H9: TR 93.0% | I9: 95.0% (94.4-95.5) | J9: 97.1% (96.3-97.8) | K9: 30 | L9: 66.1% (61.3-70.7) (n=384) | M9: 6.7% (5.8-7.6) | N9: 37.9% (36.0-39.8) | O9: 5.0 / 2.7% (1.4-5.2) | P9: 0.0% (0.0-1.3) | Q9: IP2Location 97.5% (97.2-97.8) / MaxMind 15.1% (13.0-17.5) | R9: ='Cost'!H11 | S9: 7.65 | T9: 2 GB for $15.30, subscription
A10: NodeMaven | B10: 99.1% (99.0-99.2) | C10: 1.34 / 3.30 | D10: 21830 of 28550 | E10: 0.23537653 | F10: 99.9% (99.9-99.9) | G10: 0.0081611208 | H10: US 96.6% | I10: 95.4% (94.8-95.9) | J10: 98.1% (97.4-98.6) | K10: 30 | L10: 59.4% (54.4-64.2) (n=384) | M10: 47.3% (45.4-49.1) | N10: 26.3% (24.2-28.5) | O10: 3.3 / 0.3% (0.1-1.9) | P10: 0.0% (0.0-1.3) | Q10: IP2Location 99.2% (99.0-99.4) / MaxMind 97.4% (96.2-98.2) | R10: ='Cost'!H12 | S10: 5 | T10: 2 GB for $10, one-time
A11: Oxylabs | B11: 99.8% (99.7-99.8) | C11: 0.86 / 1.53 | D11: 23216 of 28728 | E11: 0.19186856 | F11: 99.9% (99.8-99.9) | G11: 0.11675021 | H11: UA 99.5% | I11: 97.0% (96.5-97.4) | J11: 99.7% (99.3-99.8) | K11: 30 | L11: 78.4% (74.0-82.2) (n=384) | M11: 23.5% (22.0-25.1) | N11: 38.0% (36.1-40.0) | O11: 2.9 / 0.3% (0.1-1.9) | P11: 0.0% (0.0-1.3) | Q11: IP2Location 96.3% (96.0-96.7) / MaxMind 17.4% (15.2-19.9) | R11: ='Cost'!H13 | S11: 7.5 | T11: 4 GB for $30, subscription only
A12: ProxyEmpire | B12: 99.5% (99.4-99.6) | C12: 1.07 / 2.43 | D12: 22848 of 28663 | E12: 0.20287479 | F12: 99.9% (99.9-99.9) | G12: 0.15389178 | H12: US 98.1% | I12: 96.0% (95.4-96.5) | J12: 98.6% (98.0-99.0) | K12: 7.5 | L12: 1.6% (0.7-3.4) (n=384) | M12: 31.0% (29.3-32.7) | N12: 28.0% (26.0-30.1) | O12: 3.0 / 0.7% (0.2-2.4) | P12: 0.0% (0.0-1.3) | Q12: IP2Location 97.5% (97.2-97.8) / MaxMind 76.6% (73.9-79.1) | R12: ='Cost'!H14 | S12: 9 | T12: 1 GB for $9, one-time
A13: ResiProx | B13: 99.4% (99.3-99.5) | C13: 1.11 / 2.21 | D13: 19215 of 28630 | E13: 0.32885086 | F13: 99.9% (99.9-99.9) | G13: 0.30761439 | H13: ID 98.4% | I13: 95.0% (94.4-95.5) | J13: 98.8% (98.3-99.2) | K13: 16 | L13: 31.5% (27.1-36.3) (n=384) | M13: 10.4% (9.4-11.6) | N13: 30.1% (28.1-32.2) | O13: 2.6 / 0.3% (0.1-1.9) | P13: 0.0% (0.0-1.3) | Q13: IP2Location 95.2% (94.8-95.6) / MaxMind 48.0% (44.9-51.1) | R13: ='Cost'!H15 | S13: 6 | T13: 1 GB for $6, subscription
A14: SOAX | B14: 99.7% (99.7-99.8) | C14: 0.96 / 1.79 | D14: 16450 of 28727 | E14: 0.42736798 | F14: 99.9% (99.8-99.9) | G14: 0.072440561 | H14: DE 99.5% | I14: 96.4% (95.8-96.8) | J14: 96.5% (95.7-97.2) | K14: 15.25 | L14: 37.0% (32.3-41.9) (n=384) | M14: 41.1% (39.3-42.9) | N14: 19.7% (17.9-21.7) | O14: 3.4 / 1.3% (0.5-3.4) | P14: 0.0% (0.0-1.3) | Q14: IP2Location 99.1% (98.9-99.3) / MaxMind 88.9% (86.8-90.7) | R14: ='Cost'!H16 | S14: 4.6 | T14: $25 top-up (25 credits, expire in 60 days)

Sheet Infra by server
A1: Infrastructure test: https://www.cloudflare.com/cdn-cgi/trace, new IP on every request, 30 s timeout.
A3: Provider | B3: Server | C3: Requests | D3: Successful | E3: Success Rate | F3: CI low | G3: CI high | H3: Latency median, s | I3: Latency P90, s | J3: Unique IPs | K3: Duplicate Rate | L3: Geo Accuracy | M3: IPv6 share
A4: Floppydata | B4: USA (Ashburn) | C4: 9600 | D4: 9461 | E4: 0.98552083 | F4: 0.98292962 | G4: 0.98772362 | H4: 1.716 | I4: 4.408 | J4: 8785 | K4: 0.071451221 | L4: 0.99883733 | M4: 0.49741042
A5: Floppydata | B5: Germany (Falkenstein) | C5: 9600 | D5: 9472 | E5: 0.98666667 | F5: 0.98416978 | G5: 0.98877421 | H5: 0.877 | I5: 1.51 | J5: 8766 | K5: 0.074535473 | L5: 0.99820524 | M5: 0.50095017
A6: Floppydata | B6: Singapore | C6: 9600 | D6: 9460 | E6: 0.98541667 | F6: 0.98281707 | G6: 0.98762792 | H6: 0.955 | I6: 1.844 | J6: 8762 | K6: 0.073784355 | L6: 0.9987315 | M6: 0.50338266
A7: Floppydata | B7: All servers | C7: 28800 | D7: 28393 | E7: 0.98586806 | F7: 0.98443857 | G7: 0.98716794 | H7: 1.115 | I7: 2.416 | J7: 23743 | K7: 0.16377276 | L7: 0.9985912 | M7: 0.50058113
A8: Byteful | B8: USA (Ashburn) | C8: 9600 | D8: 9566 | E8: 0.99645833 | F8: 0.99505513 | G8: 0.99746437 | H8: 0.688 | I8: 1.227 | J8: 7979 | K8: 0.16590006 | L8: 0.99958185 | M8: 0.0068994355
A9: Byteful | B9: Germany (Falkenstein) | C9: 9600 | D9: 9567 | E9: 0.9965625 | F9: 0.99517654 | G9: 0.9975512 | H9: 0.527 | I9: 1.048 | J9: 7909 | K9: 0.17330407 | L9: 0.9995819 | M9: 0.0049127208
A10: Byteful | B10: Singapore | C10: 9600 | D10: 9571 | E10: 0.99697917 | F10: 0.99566492 | G10: 0.99789582 | H10: 0.938 | I10: 1.584 | J10: 8212 | K10: 0.14199143 | L10: 1 | M10: 0.0066868666
A11: Byteful | B11: All servers | C11: 28800 | D11: 28704 | E11: 0.99666667 | F11: 0.99593149 | G11: 0.99726936 | H11: 0.731 | I11: 1.301 | J11: 19989 | K11: 0.30361622 | L11: 0.99972129 | M11: 0.006166388
A12: DataImpulse | B12: USA (Ashburn) | C12: 9600 | D12: 9534 | E12: 0.993125 | F12: 0.9912634 | G12: 0.99459209 | H12: 0.9295 | I12: 3.154 | J12: 6748 | K12: 0.29221733 | L12: 0.93245228 | M12: 0.075204531
A13: DataImpulse | B13: Germany (Falkenstein) | C13: 9600 | D13: 9542 | E13: 0.99395833 | F13: 0.99219833 | G13: 0.99532316 | H13: 0.805 | I13: 2.93 | J13: 6732 | K13: 0.29448753 | L13: 0.93429051 | M13: 0.073779082
A14: DataImpulse | B14: Singapore | C14: 9600 | D14: 9534 | E14: 0.993125 | F14: 0.9912634 | G14: 0.99459209 | H14: 1.011 | I14: 2.795 | J14: 6869 | K14: 0.27952591 | L14: 0.92584435 | M14: 0.080239144
A15: DataImpulse | B15: All servers | C15: 28800 | D15: 28610 | E15: 0.99340278 | F15: 0.99239974 | G15: 0.9942742 | H15: 0.936 | I15: 2.922 | J15: 14507 | K15: 0.49293953 | L15: 0.93086333 | M15: 0.076406851
... A47: SOAX | B47: All servers | C47: 28800 | D47: 28727 | E47: 0.99746528 | F47: 0.99681446 | G47: 0.9979834 | H47: 0.96 | I47: 1.786 | J47: 16450 | K47: 0.42736798 | L47: 0.99860758 | M47: 0.072440561

Sheet Infra errors
A1: Provider | B1: Error type | C1: Count | D1: Share of all requests
A2: Byteful | B2: ssl_error | C2: 54 | D2: 0.001875
A3: Byteful | B3: timeout | C3: 26 | D3: 0.00090277778
A4: Byteful | B4: other: Remote end closed connection without response | C4: 16 | D4: 0.00055555556
A5: DataImpulse | B5: ssl_error | C5: 117 | D5: 0.0040625
A6: DataImpulse | B6: other: Remote end closed connection without response | C6: 46 | D6: 0.0015972222
A7: DataImpulse | B7: timeout | C7: 26 | D7: 0.00090277778
A8: DataImpulse | B8: tunnel_failed_502 | C8: 1 | D8: 3.4722222e-05
A9: Decodo | B9: other: Remote end closed connection without response | C9: 19 | D9: 0.00065972222
A10: Decodo | B10: tunnel_failed_522 | C10: 18 | D10: 0.000625
A11: Decodo | B11: ssl_error | C11: 11 | D11: 0.00038194444
A12: Decodo | B12: timeout | C12: 6 | D12: 0.00020833333
A13: Decodo | B13: http_502 | C13: 1 | D13: 3.4722222e-05
... A48: SOAX | B48: tunnel_failed_502 | C48: 5 | D48: 0.00017361111

Sheet Performance by GEO
A1: Provider | B1: Country | C1: Requests | D1: Success Rate | E1: CI low | F1: CI high | G1: Latency median, s | H1: Latency P90, s | I1: Geo Accuracy | J1: Unique IPs
A2: Floppydata | B2: US | C2: 2400 | D2: 0.98625 | E2: 0.98075321 | F2: 0.99019263 | G2: 1.059 | H2: 2.117 | I2: 0.99662019 | J2: 2275
A3: Floppydata | B3: DE | C3: 2400 | D3: 0.98958333 | E3: 0.98466744 | F3: 0.99293441 | G3: 0.848 | H3: 4.539 | I3: 0.99957895 | J3: 1884
A4: Floppydata | B4: GB | C4: 2400 | D4: 0.98458333 | E4: 0.9788232 | F4: 0.98879464 | G4: 0.874 | H4: 2.064 | I4: 0.99915362 | J4: 1757
A5: Floppydata | B5: FR | C5: 2400 | D5: 0.98583333 | E5: 0.98026923 | F5: 0.98984461 | G5: 0.9695 | H5: 2.361 | I5: 0.9898563 | J5: 2197
A6: Floppydata | B6: ES | C6: 2400 | D6: 0.98208333 | E6: 0.97595443 | F6: 0.98667139 | G6: 1.051 | H6: 2.453 | I6: 0.99957573 | J6: 1976
A7: Floppydata | B7: BR | C7: 2400 | D7: 0.98291667 | E7: 0.97690753 | F7: 0.9873823 | G7: 1.565 | H7: 2.481 | I7: 1 | J7: 2029
A8: Floppydata | B8: IN | C8: 2400 | D8: 0.98208333 | E8: 0.97595443 | F8: 0.98667139 | G8: 1.411 | H8: 2.48 | I8: 1 | J8: 2229
A9: Floppydata | B9: PL | C9: 2400 | D9: 0.99125 | E9: 0.98666001 | F9: 0.99426985 | G9: 0.967 | H9: 1.741 | I9: 0.99957966 | J9: 1925
A10: Floppydata | B10: UA | C10: 2400 | D10: 0.98708333 | E10: 0.98172436 | F10: 0.99088548 | G10: 1.048 | H10: 1.662 | I10: 0.99915576 | J10: 1899
A11: Floppydata | B11: TR | C11: 2400 | D11: 0.98916667 | E11: 0.98417346 | F11: 0.99259639 | G11: 1.4315 | H11: 2.555 | I11: 0.99957877 | J11: 1932
A12: Floppydata | B12: VN | C12: 2400 | D12: 0.98208333 | E12: 0.97595443 | F12: 0.98667139 | G12: 1.279 | H12: 2.513 | I12: 1 | J12: 1709
A13: Floppydata | B13: ID | C13: 2400 | D13: 0.9875 | E13: 0.98221164 | F13: 0.9912302 | G13: 1.2845 | H13: 2.96 | I13: 1 | J13: 1931
... A133: SOAX | B133: ID | C133: 2400 | D133: 0.99625 | E133: 0.99288801 | F133: 0.99802586 | G133: 1.076 | H133: 1.773 | I133: 1 | J133: 1649

Sheet GEO Success pivot
A1: Success Rate by requested country, pooled over three servers.
A3: Provider | B3: US | C3: DE | D3: GB | E3: FR | F3: ES | G3: BR | H3: IN | I3: PL | J3: UA | K3: TR | L3: VN | M3: ID
A4: Floppydata | B4: 0.98625 | C4: 0.98958333 | D4: 0.98458333 | E4: 0.98583333 | F4: 0.98208333 | G4: 0.98291667 | H4: 0.98208333 | I4: 0.99125 | J4: 0.98708333 | K4: 0.98916667 | L4: 0.98208333 | M4: 0.9875
A5: Byteful | B5: 0.99791667 | C5: 0.9925 | D5: 0.99583333 | E5: 0.99833333 | F5: 0.99875 | G5: 0.9975 | H5: 0.99208333 | I5: 0.99833333 | J5: 0.99791667 | K5: 0.99625 | L5: 0.9975 | M5: 0.99708333
A6: DataImpulse | B6: 0.99458333 | C6: 0.99125 | D6: 0.99708333 | E6: 0.9975 | F6: 1 | G6: 0.99708333 | H6: 0.98291667 | I6: 0.99958333 | J6: 0.99625 | K6: 0.9975 | L6: 0.96958333 | M6: 0.9975
A7: Decodo | B7: 0.99708333 | C7: 0.99791667 | D7: 0.99875 | E7: 0.99916667 | F7: 0.99958333 | G7: 0.99833333 | H7: 0.99583333 | I7: 0.99875 | J7: 0.99833333 | K7: 0.9975 | L7: 0.99791667 | M7: 0.9975
A8: Evomi | B8: 0.98791667 | C8: 0.98791667 | D8: 0.98416667 | E8: 0.98375 | F8: 0.9875 | G8: 0.98583333 | H8: 0.9825 | I8: 0.98416667 | J8: 0.98875 | K8: 0.98541667 | L8: 0.99208333 | M8: 0.98958333
A9: IPRoyal | B9: 0.99958333 | C9: 0.99041667 | D9: 0.99833333 | E9: 0.99708333 | F9: 0.99916667 | G9: 0.99625 | H9: 0.97583333 | I9: 0.995 | J9: 0.98541667 | K9: 0.93041667 | L9: 0.99708333 | M9: 0.99458333
A10: NodeMaven | B10: 0.96583333 | C10: 0.98875 | D10: 0.99541667 | E10: 0.99291667 | F10: 0.99041667 | G10: 0.99458333 | H10: 0.99166667 | I10: 0.99708333 | J10: 0.99625 | K10: 0.99375 | L10: 0.99541667 | M10: 0.99375
A11: Oxylabs | B11: 0.99666667 | C11: 0.99875 | D11: 0.99833333 | E11: 0.99875 | F11: 0.9975 | G11: 0.9975 | H11: 0.99541667 | I11: 0.99958333 | J11: 0.995 | K11: 0.99833333 | L11: 0.99833333 | M11: 0.99583333
A12: ProxyEmpire | B12: 0.98083333 | C12: 0.9975 | D12: 0.99666667 | E12: 0.99708333 | F12: 0.99708333 | G12: 0.99708333 | H12: 0.99208333 | I12: 0.99833333 | J12: 0.99791667 | K12: 0.99416667 | L12: 0.99791667 | M12: 0.99625
A13: ResiProx | B13: 0.98958333 | C13: 0.99916667 | D13: 0.9975 | E13: 0.99875 | F13: 0.9975 | G13: 0.99625 | H13: 0.98583333 | I13: 0.9975 | J13: 0.99625 | K13: 0.99208333 | L13: 0.99458333 | M13: 0.98416667
A14: SOAX | B14: 0.9975 | C14: 0.99541667 | D14: 0.99666667 | E14: 0.99583333 | F14: 0.99916667 | G14: 0.99958333 | H14: 0.9975 | I14: 0.99875 | J14: 0.99708333 | K14: 0.99625 | L14: 0.99958333 | M14: 0.99625

Sheet GEO Accuracy pivot
A1: Geo Accuracy by requested country, pooled over three servers.
A3: Provider | B3: US | C3: DE | D3: GB | E3: FR | F3: ES | G3: BR | H3: IN | I3: PL | J3: UA | K3: TR | L3: VN | M3: ID
A4: Floppydata | B4: 0.99662019 | C4: 0.99957895 | D4: 0.99915362 | E4: 0.9898563 | F4: 0.99957573 | G4: 1 | H4: 1 | I4: 0.99957966 | J4: 0.99915576 | K4: 0.99957877 | L4: 1 | M4: 1
A5: Byteful | B5: 1 | C5: 0.99958018 | D5: 1 | E5: 1 | F5: 0.99916562 | G5: 1 | H5: 1 | I5: 1 | J5: 0.99916493 | K5: 0.99916353 | L5: 1 | M5: 0.99958211
A6: DataImpulse | B6: 0.99916213 | C6: 1 | D6: 0.99832846 | E6: 0.99415205 | F6: 1 | G6: 1 | H6: 0.99872827 | I6: 1 | J6: 0.99790882 | K6: 0.18546366 | L6: 1 | M6: 1
A7: Decodo | B7: 1 | C7: 1 | D7: 1 | E7: 1 | F7: 1 | G7: 1 | H7: 1 | I7: 1 | J7: 0.99707846 | K7: 0.99415205 | L7: 1 | M7: 1
A8: Evomi | B8: 0.99915647 | C8: 0.99915647 | D8: 0.99957663 | E8: 0.97882253 | F8: 1 | G8: 1 | H8: 1 | I8: 1 | J8: 1 | K8: 0.99957717 | L8: 1 | M8: 1
A9: IPRoyal | B9: 1 | C9: 1 | D9: 1 | E9: 1 | F9: 1 | G9: 1 | H9: 1 | I9: 1 | J9: 1 | K9: 0.99865652 | L9: 1 | M9: 1
A10: NodeMaven | B10: 1 | C10: 0.99873578 | D10: 0.99832566 | E10: 0.99958036 | F10: 1 | G10: 1 | H10: 0.99915966 | I10: 0.99916423 | J10: 0.99790882 | K10: 0.99622642 | L10: 1 | M10: 0.99916143
A11: Oxylabs | B11: 1 | C11: 1 | D11: 1 | E11: 1 | F11: 0.99958229 | G11: 1 | H11: 1 | I11: 0.99958316 | J11: 0.99371859 | K11: 0.98956594 | L11: 1 | M11: 1
A12: ProxyEmpire | B12: 1 | C12: 0.99916458 | D12: 0.99958194 | E12: 1 | F12: 0.99958211 | G12: 1 | H12: 1 | I12: 0.99958264 | J12: 0.99582463 | K12: 0.99706622 | L12: 1 | M12: 0.99958176
A13: ResiProx | B13: 0.99957895 | C13: 0.99958299 | D13: 0.99874687 | E13: 0.99958281 | F13: 0.99916458 | G13: 1 | H13: 0.99957735 | I13: 1 | J13: 0.99289 | K13: 0.99958001 | L13: 1 | M13: 1
A14: SOAX | B14: 1 | C14: 0.99874424 | D14: 0.99665552 | E14: 1 | F14: 1 | G14: 1 | H14: 0.99916458 | I14: 0.99958281 | J14: 0.99289595 | K14: 0.99623588 | L14: 1 | M14: 1

Sheet Targets
A1: Google search (12 countries) and the Instagram profile page of @instagram (US, DE, GB) as a phone browser (curl_cffi, Chrome 131 Android TLS fingerprint), no JavaScript. Google 'turn on JavaScript' and consent pages count as let in.
A3: Provider | B3: Target | C3: Server | D3: Requests | E3: Success | F3: Target Success Rate | G3: CI low | H3: CI high | I3: CAPTCHA | J3: Blocked / login wall / rate limited | K3: Other errors | L3: Refused by the proxy (excluded) | M3: Latency median, s | N3: Latency P90, s | O3: Avg page, KB (decoded)
A4: Floppydata | B4: google | C4: USA (Ashburn) | D4: 1920 | E4: 1876 | F4: 0.97708333 | G4: 0.96937644 | H4: 0.98288491 | I4: 0.0041666667 | J4: 0 | K4: 0.01875 | L4: 0 | M4: 2.037 | N4: 4.338 | O4: 88.766225
A5: Floppydata | B5: google | C5: Germany (Falkenstein) | D5: 1920 | E5: 1881 | F5: 0.9796875 | G5: 0.97235356 | H5: 0.98510572 | I5: 0.0041666667 | J5: 0 | K5: 0.016145833 | L5: 0 | M5: 1.193 | N5: 2.566 | O5: 89.061584
A6: Floppydata | B6: google | C6: Singapore | D6: 1920 | E6: 1875 | F6: 0.9765625 | G6: 0.96878376 | H6: 0.982438 | I6: 0.0067708333 | J6: 0 | K6: 0.016666667 | L6: 0 | M6: 1.349 | N6: 2.792 | O6: 88.787559
A7: Floppydata | B7: google | C7: All servers | D7: 5760 | E7: 5632 | F7: 0.97777778 | G7: 0.97364052 | H7: 0.98127816 | I7: 0.0050347222 | J7: 0 | K7: 0.0171875 | L7: 0 | M7: 1.5085 | N7: 3.267 | O7: 88.87179
A8: Floppydata | B8: instagram | C8: USA (Ashburn) | D8: 720 | E8: 703 | F8: 0.97638889 | G8: 0.96251406 | H8: 0.9852071 | I8: 0 | J8: 0.0013888889 | K8: 0.022222222 | L8: 0 | M8: 1.865 | N8: 5.4172 | O8: 844.23072
A9: Floppydata | B9: instagram | C9: Germany (Falkenstein) | D9: 720 | E9: 704 | F9: 0.97777778 | G9: 0.96420817 | H9: 0.98627602 | I9: 0 | J9: 0.0013888889 | K9: 0.020833333 | L9: 0 | M9: 1.3515 | N9: 3.3469 | O9: 846.08366
A10: Floppydata | B10: instagram | C10: Singapore | D10: 720 | E10: 691 | F10: 0.95972222 | G10: 0.94275285 | H10: 0.97181188 | I10: 0 | J10: 0.0055555556 | K10: 0.034722222 | L10: 0 | M10: 1.701 | N10: 4.002 | O10: 832.06856
A11: Floppydata | B11: instagram | C11: All servers | D11: 2160 | E11: 2098 | F11: 0.9712963 | G11: 0.9633746 | H11: 0.97754455 | I11: 0 | J11: 0.0027777778 | K11: 0.025925926 | L11: 0 | M11: 1.655 | N11: 4.0973 | O11: 840.79431
A12: Byteful | B12: google | C12: USA (Ashburn) | D12: 1920 | E12: 1835 | F12: 0.95572917 | G12: 0.94558247 | H12: 0.96405583 | I12: 0.034895833 | J12: 0 | K12: 0.009375 | L12: 0 | M12: 1.169 | N12: 2.0952 | O12: 86.973131
A13: Byteful | B13: google | C13: Germany (Falkenstein) | D13: 1920 | E13: 1834 | F13: 0.95520833 | G13: 0.94501164 | H13: 0.96358707 | I13: 0.036979167 | J13: 0 | K13: 0.0078125 | L13: 0 | M13: 0.9195 | N13: 1.933 | O13: 86.93759
A14: Byteful | B14: google | C14: Singapore | D14: 1920 | E14: 1832 | F14: 0.95416667 | G14: 0.94387098 | H14: 0.96264856 | I14: 0.041145833 | J14: 0 | K14: 0.0046875 | L14: 0 | M14: 1.5735 | N14: 2.8938 | O14: 86.857163
A15: Byteful | B15: google | C15: All servers | D15: 5760 | E15: 5501 | F15: 0.95503472 | G15: 0.94937292 | H15: 0.96008996 | I15: 0.037673611 | J15: 0 | K15: 0.0072916667 | L15: 0 | M15: 1.289 | N15: 2.365 | O15: 86.922628
... A91: SOAX | B91: instagram | C91: All servers | D91: 2160 | E91: 2085 | F91: 0.96527778 | G91: 0.95669375 | H91: 0.97220973 | I91: 0 | J91: 0.013425926 | K91: 0.021296296 | L91: 0 | M91: 1.582 | N91: 3.3146 | O91: 838.54896

Sheet Sticky
A1: 8 sessions per run asking for a 30-minute sticky IP, one check every 30 s. The lifetime ends at the first other IP or at 3 failed checks in a row; an IP change at or after 30 minutes counts as kept.
A3: Provider | B3: Server | C3: Sessions | D3: Median IP lifetime, min | E3: Lived >= 10 min | F3: Lived 30 min | G3: CI low (30 min) | H3: CI high (30 min) | I3: Failed checks
A4: Floppydata | B4: USA (Ashburn) | C4: 128 | D4: 18.5 | E4: 0.609375 | F4: 0.375 | G4: 0.29592294 | H4: 0.46136156 | I4: 0.0058913934
A5: Floppydata | B5: Germany (Falkenstein) | C5: 128 | D5: 5.75 | E5: 0.421875 | F5: 0.2578125 | G5: 0.18986792 | H5: 0.33987079 | I5: 0.0056352459
A6: Floppydata | B6: Singapore | C6: 128 | D6: 2.25 | E6: 0.3671875 | F6: 0.1953125 | G6: 0.13593869 | H6: 0.27244227 | I6: 0.0069159836
A7: Floppydata | B7: All servers | C7: 384 | D7: 8 | E7: 0.46614583 | F7: 0.27604167 | G7: 0.23371364 | H7: 0.32280634 | I7: 0.006147541
A8: Byteful | B8: USA (Ashburn) | C8: 128 | D8: 30 | E8: 0.828125 | F8: 0.734375 | G8: 0.65184546 | H8: 0.80324611 | I8: 0.0098616803
A9: Byteful | B9: Germany (Falkenstein) | C9: 128 | D9: 30 | E9: 0.8046875 | F9: 0.6796875 | G9: 0.5946325 | H9: 0.75427104 | I9: 0.030737705
A10: Byteful | B10: Singapore | C10: 128 | D10: 12.75 | E10: 0.515625 | F10: 0.28125 | G10: 0.21061207 | H10: 0.3646358 | I10: 0.023181352
A11: Byteful | B11: All servers | C11: 384 | D11: 30 | E11: 0.71614583 | F11: 0.56510417 | G11: 0.51511661 | H11: 0.613802 | I11: 0.021260246
A12: DataImpulse | B12: USA (Ashburn) | C12: 128 | D12: 30 | E12: 0.8828125 | F12: 0.7578125 | G12: 0.67678704 | H12: 0.82381368 | I12: 0.010245902
A13: DataImpulse | B13: Germany (Falkenstein) | C13: 128 | D13: 30 | E13: 0.859375 | F13: 0.7265625 | G13: 0.64359071 | H13: 0.79633114 | I13: 0.011782787
A14: DataImpulse | B14: Singapore | C14: 128 | D14: 30 | E14: 0.8203125 | F14: 0.6875 | G14: 0.60272733 | H14: 0.76134592 | I14: 0.018954918
A15: DataImpulse | B15: All servers | C15: 384 | D15: 30 | E15: 0.85416667 | F15: 0.72395833 | G15: 0.67719366 | H15: 0.76628636 | I15: 0.013661202
... A47: SOAX | B47: All servers | C47: 384 | D47: 15.25 | E47: 0.6171875 | F47: 0.36979167 | G47: 0.32301894 | H47: 0.41914384 | I47: 0.00093920765

Sheet Trend Sticky by run
A1: Share of sessions that kept the IP 30 minutes, per run (24 sessions per provider per run). Small samples: a trend, not a ranking.
A3: Provider | B3: 20261024-0330 | C3: 20261024-0930 | D3: 20261024-1530 | E3: 20261024-2130 | F3: 20261025-0330 | G3: 20261025-0930 | H3: 20261025-1530 | I3: 20261025-2130 | J3: 20261026-0330 | K3: 20261026-0930 | L3: 20261026-1530 | M3: 20261026-2130 | N3: 20261027-0330 | O3: 20261027-0930 | P3: 20261027-1530 | Q3: 20261027-2130
A4: Floppydata | B4: 0.375 | C4: 0.20833333 | D4: 0.33333333 | E4: 0.29166667 | F4: 0.41666667 | G4: 0.41666667 | H4: 0.29166667 | I4: 0.29166667 | J4: 0.29166667 | K4: 0.33333333 | L4: 0.125 | M4: 0.125 | N4: 0.33333333 | O4: 0.25 | P4: 0.20833333 | Q4: 0.125
A5: Byteful | B5: 0.54166667 | C5: 0.66666667 | D5: 0.45833333 | E5: 0.79166667 | F5: 0.54166667 | G5: 0.70833333 | H5: 0.625 | I5: 0.5 | J5: 0.41666667 | K5: 0.66666667 | L5: 0.5 | M5: 0.58333333 | N5: 0.58333333 | O5: 0.41666667 | P5: 0.5 | Q5: 0.54166667
A6: DataImpulse | B6: 0.75 | C6: 0.5 | D6: 0.875 | E6: 0.66666667 | F6: 0.875 | G6: 0.79166667 | H6: 0.70833333 | I6: 0.70833333 | J6: 0.70833333 | K6: 0.70833333 | L6: 0.70833333 | M6: 0.83333333 | N6: 0.91666667 | O6: 0.625 | P6: 0.58333333 | Q6: 0.625
A7: Decodo | B7: 0.91666667 | C7: 0.83333333 | D7: 0.83333333 | E7: 0.91666667 | F7: 0.875 | G7: 0.83333333 | H7: 0.875 | I7: 0.75 | J7: 0.83333333 | K7: 0.66666667 | L7: 0.625 | M7: 0.79166667 | N7: 0.58333333 | O7: 0.5 | P7: 0.875 | Q7: 0.875
A8: Evomi | B8: 0.54166667 | C8: 0.58333333 | D8: 0.375 | E8: 0.5 | F8: 0.66666667 | G8: 0.5 | H8: 0.5 | I8: 0.625 | J8: 0.5 | K8: 0.66666667 | L8: 0.66666667 | M8: 0.54166667 | N8: 0.79166667 | O8: 0.41666667 | P8: 0.45833333 | Q8: 0.375
A9: IPRoyal | B9: 0.83333333 | C9: 0.83333333 | D9: 0.75 | E9: 0.75 | F9: 0.75 | G9: 0.79166667 | H9: 0.75 | I9: 0.79166667 | J9: 0.70833333 | K9: 0.66666667 | L9: 0.54166667 | M9: 0.58333333 | N9: 0.5 | O9: 0.45833333 | P9: 0.41666667 | Q9: 0.45833333
A10: NodeMaven | B10: 0.54166667 | C10: 0.625 | D10: 0.45833333 | E10: 0.66666667 | F10: 0.83333333 | G10: 0.58333333 | H10: 0.75 | I10: 0.33333333 | J10: 0.75 | K10: 0.45833333 | L10: 0.54166667 | M10: 0.54166667 | N10: 0.625 | O10: 0.625 | P10: 0.66666667 | Q10: 0.5
A11: Oxylabs | B11: 0.83333333 | C11: 0.79166667 | D11: 0.875 | E11: 0.83333333 | F11: 0.83333333 | G11: 0.91666667 | H11: 0.91666667 | I11: 0.91666667 | J11: 0.875 | K11: 0.83333333 | L11: 0.58333333 | M11: 0.75 | N11: 0.54166667 | O11: 0.45833333 | P11: 0.875 | Q11: 0.70833333
A12: ProxyEmpire | B12: 0 | C12: 0 | D12: 0 | E12: 0 | F12: 0.041666667 | G12: 0 | H12: 0 | I12: 0.041666667 | J12: 0 | K12: 0 | L12: 0.041666667 | M12: 0.041666667 | N12: 0 | O12: 0 | P12: 0 | Q12: 0.083333333
A13: ResiProx | B13: 0.625 | C13: 0.125 | D13: 0.083333333 | E13: 0.041666667 | F13: 0.45833333 | G13: 0.33333333 | H13: 0.083333333 | I13: 0.20833333 | J13: 0.58333333 | K13: 0.33333333 | L13: 0.083333333 | M13: 0.41666667 | N13: 0.58333333 | O13: 0.125 | P13: 0.41666667 | Q13: 0.54166667
A14: SOAX | B14: 0.45833333 | C14: 0.20833333 | D14: 0.375 | E14: 0.54166667 | F14: 0.33333333 | G14: 0.45833333 | H14: 0.25 | I14: 0.33333333 | J14: 0.45833333 | K14: 0.45833333 | L14: 0.29166667 | M14: 0.41666667 | N14: 0.25 | O14: 0.33333333 | P14: 0.375 | Q14: 0.375

Sheet Fingerprint
A1: p0f 3 on our own HTTPS endpoint (de server); the exit device opens the TCP connection. Checked with a real iPhone on 5G (Mac OS X, tunnel-sized MTU) and on home Wi-Fi (Mac OS X, DSL). Android check pending.
A3: Provider | B3: Requests | C3: Answers | D3: Linux (incl. Android) | E3: Windows | F3: Mac OS X / iOS | G3: Other | H3: Unknown | I3: Ethernet MTU 1500 | J3: Tunnel-sized MTU (typical mobile)
A4: Floppydata | B4: 2880 | C4: 2758 | D4: 0.79187817 | E4: 0.0021754895 | F4: 0.016678753 | G4: 0.060188542 | H4: 0.12907904 | I4: 0.22871995 | J4: 0.62443145
A5: Byteful | B5: 2880 | C5: 2786 | D5: 0.38513999 | E5: 0.49282125 | F5: 0.00071787509 | G5: 0.047379756 | H5: 0.073941134 | I5: 0.2931677 | J5: 0.53975155
A6: DataImpulse | B6: 2880 | C6: 2799 | D6: 0.78313683 | E6: 0.11575563 | F6: 0 | G6: 0.023222579 | H6: 0.077884959 | I6: 0.4122449 | J6: 0.4361516
A7: Decodo | B7: 2880 | C7: 2785 | D7: 0.73895871 | E7: 0.24452424 | F7: 0 | G7: 0.0032315978 | H7: 0.013285458 | I7: 0.37735094 | J7: 0.13645458
A8: Evomi | B8: 2880 | C8: 2832 | D8: 0.6924435 | E8: 0.18008475 | F8: 0 | G8: 0.043785311 | H8: 0.083686441 | I8: 0.22613065 | J8: 0.66771357
A9: IPRoyal | B9: 2880 | C9: 2849 | D9: 0.9020709 | E9: 0.066690067 | F9: 0.0098280098 | G9: 0.0024570025 | H9: 0.018954019 | I9: 0.37866887 | J9: 0.16122365
A10: NodeMaven | B10: 2880 | C10: 2802 | D10: 0.41291934 | E10: 0.47251963 | F10: 0 | G10: 0.042112777 | H10: 0.072448251 | I10: 0.2629256 | J10: 0.60718789
A11: Oxylabs | B11: 2880 | C11: 2776 | D11: 0.75036023 | E11: 0.23523055 | F11: 0.00036023055 | G11: 0.0054034582 | H11: 0.0086455331 | I11: 0.38039532 | J11: 0.14925373
A12: ProxyEmpire | B12: 2880 | C12: 2825 | D12: 0.56814159 | E12: 0.3100885 | F12: 0.0007079646 | G12: 0.04460177 | H12: 0.076460177 | I12: 0.27988827 | J12: 0.45418994
A13: ResiProx | B13: 2880 | C13: 2834 | D13: 0.7833451 | E13: 0.10444601 | F13: 0 | G13: 0.050458716 | H13: 0.061750176 | I13: 0.3011022 | J13: 0.29809619
A14: SOAX | B14: 2880 | C14: 2837 | D14: 0.47268241 | E14: 0.41099753 | F14: 0.0074021854 | G14: 0.046880508 | H14: 0.062037363 | I14: 0.19730392 | J14: 0.54963235

Sheet IP quality
A1: Scamalytics API v3 and IPinfo Lite on a sample of unique exit IPs per provider, spread evenly over the 12 countries.
A3: Provider | B3: IPs checked | C3: Fraud Score avg (0-100) | D3: Fraud Score median | E3: High risk share | F3: CI low | G3: CI high | H3: Proxy flags | I3: Datacenter | J3: VPN | K3: Hosting ASN (name heuristic) | L3: Geo accuracy (IPinfo)
A4: Floppydata | B4: 300 | C4: 3.5133333 | D4: 1 | E4: 0.0066666667 | F4: 0.00183011 | G4: 0.023978074 | H4: 0 | I4: 0 | J4: 0 | K4: 0 | L4: 0.99666667
A5: Byteful | B5: 300 | C5: 3.5866667 | D5: 1 | E5: 0.01 | F5: 0.0034065568 | G5: 0.028984005 | H5: 0 | I5: 0 | J5: 0 | K5: 0 | L5: 1
A6: DataImpulse | B6: 300 | C6: 4.0466667 | D6: 1 | E6: 0.013333333 | F6: 0.0051968777 | G6: 0.033776061 | H6: 0 | I6: 0 | J6: 0 | K6: 0 | L6: 0.95333333
A7: Decodo | B7: 300 | C7: 2.7066667 | D7: 1 | E7: 0.0033333333 | F7: 0.00058864258 | G7: 0.018637165 | H7: 0 | I7: 0 | J7: 0 | K7: 0 | L7: 0.99666667
A8: Evomi | B8: 300 | C8: 2.7466667 | D8: 1 | E8: 0 | F8: 0 | G8: 0.01264343 | H8: 0 | I8: 0 | J8: 0 | K8: 0 | L8: 1
A9: IPRoyal | B9: 300 | C9: 4.96 | D9: 1 | E9: 0.026666667 | F9: 0.013572907 | G9: 0.05172954 | H9: 0 | I9: 0 | J9: 0 | K9: 0 | L9: 1
A10: NodeMaven | B10: 300 | C10: 3.2733333 | D10: 1 | E10: 0.0033333333 | F10: 0.00058864258 | G10: 0.018637165 | H10: 0 | I10: 0 | J10: 0 | K10: 0 | L10: 1
A11: Oxylabs | B11: 300 | C11: 2.8733333 | D11: 1 | E11: 0.0033333333 | F11: 0.00058864258 | G11: 0.018637165 | H11: 0 | I11: 0 | J11: 0 | K11: 0 | L11: 1
A12: ProxyEmpire | B12: 300 | C12: 3.0166667 | D12: 1 | E12: 0.0066666667 | F12: 0.00183011 | G12: 0.023978074 | H12: 0 | I12: 0 | J12: 0 | K12: 0 | L12: 1
A13: ResiProx | B13: 300 | C13: 2.5733333 | D13: 1 | E13: 0.0033333333 | F13: 0.00058864258 | G13: 0.018637165 | H13: 0 | I13: 0 | J13: 0 | K13: 0.0033333333 | L13: 0.99666667
A14: SOAX | B14: 300 | C14: 3.35 | D14: 1 | E14: 0.013333333 | F14: 0.0051968777 | G14: 0.033776061 | H14: 0 | I14: 0 | J14: 0 | K14: 0 | L14: 1

Sheet Mobile IP Share
A1: Unique exit IPs, up to 10,000 per provider spread over the 12 countries. IP2Location.io: usage type contains MOB (also 'ISP/MOB', which means a carrier with both fixed and mobile networks). MaxMind GeoIP2 Insights: user type cellular, on the first 1,000 IPs per provider; the last three columns use these 1,000. The two databases disagree for some providers; neither is ground truth.
A3: Provider | B3: IPs (IP2Location) | C3: Mobile by IP2Location | D3: CI low | E3: CI high | F3: IPs (MaxMind) | G3: Cellular by MaxMind | H3: CI low | I3: CI high | J3: Mobile in both | K3: IP2Location 'MOB' only | L3: IP2Location mobile, MaxMind not
A4: Floppydata | B4: 10000 | C4: 0.9508 | D4: 0.94638497 | E4: 0.9548688 | F4: 1000 | G4: 0.887 | H4: 0.86587803 | I4: 0.90515995 | J4: 0.885 | K4: 0.403 | L4: 0.075
A5: Byteful | B5: 10000 | C5: 0.9866 | D5: 0.98415223 | E5: 0.98867405 | F5: 1000 | G5: 0.972 | H5: 0.95982956 | I5: 0.98055785 | J5: 0.961 | K5: 0.478 | L5: 0.021
A6: DataImpulse | B6: 10000 | C6: 0.906 | D6: 0.90012322 | E6: 0.91156496 | F6: 1000 | G6: 0.805 | H6: 0.77929528 | I6: 0.82837031 | J6: 0.782 | K6: 0.371 | L6: 0.069
A7: Decodo | B7: 10000 | C7: 0.962 | D7: 0.95807166 | E7: 0.96557351 | F7: 1000 | G7: 0.16 | H7: 0.13858489 | I7: 0.1840174 | J7: 0.16 | K7: 0.254 | L7: 0.802
A8: Evomi | B8: 10000 | C8: 0.9926 | D8: 0.99072073 | E8: 0.99410094 | F8: 1000 | G8: 0.987 | H8: 0.97788535 | I8: 0.99238725 | J8: 0.983 | K8: 0.483 | L8: 0.01
A9: IPRoyal | B9: 10000 | C9: 0.9751 | D9: 0.97185862 | E9: 0.97797649 | F9: 1000 | G9: 0.151 | H9: 0.13014576 | I9: 0.17452541 | J9: 0.151 | K9: 0.249 | L9: 0.821
A10: NodeMaven | B10: 10000 | C10: 0.992 | D10: 0.99005516 | E10: 0.99356698 | F10: 1000 | G10: 0.974 | H10: 0.96217592 | I10: 0.98219618 | J10: 0.97 | K10: 0.497 | L10: 0.022
A11: Oxylabs | B11: 10000 | C11: 0.9634 | D11: 0.95953801 | E11: 0.96690608 | F11: 1000 | G11: 0.174 | H11: 0.15176196 | I11: 0.19873317 | J11: 0.174 | K11: 0.276 | L11: 0.79
A12: ProxyEmpire | B12: 10000 | C12: 0.9754 | D12: 0.97217645 | E12: 0.97825843 | F12: 1000 | G12: 0.766 | H12: 0.73877165 | I12: 0.79119244 | J12: 0.764 | K12: 0.475 | L12: 0.21
A13: ResiProx | B13: 10000 | C13: 0.9521 | D13: 0.94773792 | E13: 0.95611486 | F13: 1000 | G13: 0.48 | H13: 0.44917023 | I13: 0.51098284 | J13: 0.48 | K13: 0.41 | L13: 0.472
A14: SOAX | B14: 10000 | C14: 0.9912 | D14: 0.98917149 | E14: 0.99285125 | F14: 1000 | G14: 0.889 | H14: 0.86802158 | I14: 0.90700109 | J14: 0.883 | K14: 0.505 | L14: 0.104

Sheet Shared IPs
A1: Successful infrastructure requests of the whole test. The same public IP at two providers can be carrier-grade NAT (many phones behind one address) or the same device in both pools.
A3: Provider | B3: Unique exit IPs | C3: Also given out by another provider | D3: Share
A4: Floppydata | B4: 23743 | C4: 1307 | D4: 0.055047804
A5: Byteful | B5: 19989 | C5: 11132 | D5: 0.5569063
A6: DataImpulse | B6: 14507 | C6: 6026 | D6: 0.41538568
A7: Decodo | B7: 23323 | C7: 7352 | D7: 0.31522531
A8: Evomi | B8: 18270 | C8: 9648 | D8: 0.52807882
A9: IPRoyal | B9: 24661 | C9: 2487 | D9: 0.10084749
A10: NodeMaven | B10: 21830 | C10: 12312 | D10: 0.5639945
A11: Oxylabs | B11: 23216 | C11: 7369 | D11: 0.31741041
A12: ProxyEmpire | B12: 22848 | C12: 12188 | D12: 0.53343838
A13: ResiProx | B13: 19215 | C13: 5174 | D13: 0.2692688
A14: SOAX | B14: 16450 | C14: 6059 | D14: 0.36832827
A16: Provider A | B16: Provider B | C16: Shared IPs | D16: Share of A's IPs | E16: Share of B's IPs | F16: Seen at both in the same hour
A17: Byteful | B17: NodeMaven | C17: 6572 | D17: 0.32878083 | E17: 0.3010536 | F17: 0.72580645
A18: Decodo | B18: Oxylabs | C18: 5866 | D18: 0.25151138 | E18: 0.25267057 | F18: 0.42413911
A19: NodeMaven | B19: ProxyEmpire | C19: 4973 | D19: 0.22780577 | E19: 0.21765581 | F19: 0.67363764
A20: Byteful | B20: ProxyEmpire | C20: 4431 | D20: 0.22167192 | E20: 0.19393382 | F20: 0.68111036
A21: ProxyEmpire | B21: ResiProx | C21: 3849 | D21: 0.16846113 | E21: 0.20031226 | F21: 0.62223954
A22: Evomi | B22: NodeMaven | C22: 3614 | D22: 0.19781062 | E22: 0.16555199 | F22: 0.71831765
A23: DataImpulse | B23: Evomi | C23: 3489 | D23: 0.24050458 | E23: 0.1909688 | F23: 0.71023216
A24: Byteful | B24: Evomi | C24: 3062 | D24: 0.15318425 | E24: 0.16759715 | F24: 0.69072502
A25: Evomi | B25: SOAX | C25: 2645 | D25: 0.14477285 | E25: 0.16079027 | F25: 0.8120983
A26: Evomi | B26: ProxyEmpire | C26: 2537 | D26: 0.13886152 | E26: 0.11103817 | F26: 0.65786362
A27: DataImpulse | B27: NodeMaven | C27: 2509 | D27: 0.17295099 | E27: 0.11493358 | F27: 0.70785173
A28: NodeMaven | B28: SOAX | C28: 2122 | D28: 0.09720568 | E28: 0.12899696 | F28: 0.71677663
... A36: Evomi | B36: Oxylabs | C36: 647 | D36: 0.035413246 | E36: 0.027868711 | F36: 0.72333849

Sheet Cost
A1: Cost per 1,000 successful requests = price per GB x traffic by the provider's own counter / successful requests of all tests x 1,000. Fill column D with the dashboard counters read right after the test.
A2: Counters read at (UTC): 2026-10-28 06:32 ... 2026-10-28 07:45
A5: Provider | B5: Price, $/GB | C5: Minimum purchase | D5: Traffic used, MB (dashboard counter) | E5: Successful infra | F5: Successful targets | G5: Successful sticky checks + fingerprint | H5: Cost per 1,000 successful, $ | I5: Counter source
A6: Floppydata | B6: 1 | C6: 19 GB for $19 | D6: 750 | E6: 28393 | F6: 7730 | G6: 26038 | H6: =IF(ISNUMBER(D6),B6*D6/1000/(E6+F6+G6)*1000,"") | I6: Proxy > Overview > Traffic usage, filter test username + Mobile: Last 7 days 0.75 GB = Last 30 days 0.75 GB
A7: Byteful | B7: 4.25 | C7: 2 GB for $8.50, subscription | D7: 932.88 | E7: 28704 | F7: 7643 | G7: 25712 | H7: =IF(ISNUMBER(D7),B7*D7/1000/(E7+F7+G7)*1000,"") | I7: Network Observability > Overview, last 30 days, Network = Mobile: 932.88 MB (0.93 GB)
A8: DataImpulse | B8: 2 | C8: 2.5 GB for $5, one-time (new users) | D8: 872.96 | E8: 28610 | F8: 7367 | G8: 25903 | H8: =IF(ISNUMBER(D8),B8*D8/1000/(E8+F8+G8)*1000,"") | I8: Dashboard > Usage Chart 21-28 Oct Mobile Proxy / Plan 1: Total Traffic 872.96 MB
A9: Decodo | B9: 3.75 | C9: 2 GB for $7.50, subscription | D9: 1020 | E9: 28744 | F9: 7722 | G9: 23526 | H9: =IF(ISNUMBER(D9),B9*D9/1000/(E9+F9+G9)*1000,"") | I9: plan bar "2 GB plan 1.02 / 2 GB" (billed traffic)
A10: Evomi | B10: 3.98 | C10: 4 GB for $15.92, one-time | D10: 915.11 | E10: 28415 | F10: 7494 | G10: 25994 | H10: =IF(ISNUMBER(D10),B10*D10/1000/(E10+F10+G10)*1000,"") | I10: Mobile Proxies > Bandwidth Traffic last 14 days 915.11 MB
A11: IPRoyal | B11: 7.65 | C11: 2 GB for $15.30, subscription | D11: 903.93 | E11: 28462 | F11: 7570 | G11: 25862 | H11: =IF(ISNUMBER(D11),B11*D11/1000/(E11+F11+G11)*1000,"") | I11: Mobile > My statistics, Download report 23-28 Oct: total 903.925569 MB
A12: NodeMaven | B12: 5 | C12: 2 GB for $10, one-time | D12: 930 | E12: 28550 | F12: 7611 | G12: 25619 | H12: =IF(ISNUMBER(D12),B12*D12/1000/(E12+F12+G12)*1000,"") | I12: Dashboard > Statistics 7 days (test proxy user) Traffic 930 MB
A13: Oxylabs | B13: 7.5 | C13: 4 GB for $30, subscription only | D13: 905.53 | E13: 28728 | F13: 7739 | G13: 23580 | H13: =IF(ISNUMBER(D13),B13*D13/1000/(E13+F13+G13)*1000,"") | I13: Mobile Proxies > Statistics total traffic 905.53 MB (plan bar 0.91 GB / 4 GB)
A14: ProxyEmpire | B14: 9 | C14: 1 GB for $9, one-time | D14: 913.4 | E14: 28663 | F14: 7658 | G14: 26099 | H14: =IF(ISNUMBER(D14),B14*D14/1000/(E14+F14+G14)*1000,"") | I14: Past Usage > Rotating Mobile, last 14 days: Traffic 913.4 MB
A15: ResiProx | B15: 6 | C15: 1 GB for $6, subscription | D15: 905.8 | E15: 28630 | F15: 7607 | G15: 26139 | H15: =IF(ISNUMBER(D15),B15*D15/1000/(E15+F15+G15)*1000,"") | I15: Dashboard > Traffic Usage Last 20 Days: Total 905.8 MB
A16: SOAX | B16: 4.6 | C16: $25 top-up (25 credits, expire in 60 days) | D16: 912 | E16: 28727 | F16: 7633 | G16: 26239 | H16: =IF(ISNUMBER(D16),B16*D16/1000/(E16+F16+G16)*1000,"") | I16: Dashboard > Performance 7d traffic 912 MB (package mobile 100%)

Sheet Infra runs
A1: One row per provider, server and scheduled run: shows whether results are stable during the test.
A3: Provider | B3: Server | C3: Run | D3: Started (UTC) | E3: Requests | F3: Success Rate | G3: Latency median, s
A4: Byteful | B4: Germany (Falkenstein) | C4: 20261024-0800 | D4: 2026-10-24 08:02:12 | E4: 1200 | F4: 0.9975 | G4: 0.515
A5: Byteful | B5: Germany (Falkenstein) | C5: 20261024-2000 | D5: 2026-10-24 20:01:49 | E5: 1200 | F5: 0.99333333 | G5: 0.543
A6: Byteful | B6: Germany (Falkenstein) | C6: 20261025-0800 | D6: 2026-10-25 08:02:22 | E6: 1200 | F6: 0.99833333 | G6: 0.517
A7: Byteful | B7: Germany (Falkenstein) | C7: 20261025-2000 | D7: 2026-10-25 20:03:47 | E7: 1200 | F7: 0.99666667 | G7: 0.546
A8: Byteful | B8: Germany (Falkenstein) | C8: 20261026-0800 | D8: 2026-10-26 08:00:48 | E8: 1200 | F8: 0.99666667 | G8: 0.519
A9: Byteful | B9: Germany (Falkenstein) | C9: 20261026-2000 | D9: 2026-10-26 20:04:49 | E9: 1200 | F9: 0.99583333 | G9: 0.525
A10: Byteful | B10: Germany (Falkenstein) | C10: 20261027-0800 | D10: 2026-10-27 08:02:09 | E10: 1200 | F10: 0.99583333 | G10: 0.515
A11: Byteful | B11: Germany (Falkenstein) | C11: 20261027-2000 | D11: 2026-10-27 20:00:42 | E11: 1200 | F11: 0.99833333 | G11: 0.538
A12: Byteful | B12: Singapore | C12: 20261024-0800 | D12: 2026-10-24 08:04:35 | E12: 1200 | F12: 0.9975 | G12: 0.835
A13: Byteful | B13: Singapore | C13: 20261024-2000 | D13: 2026-10-24 20:03:59 | E13: 1200 | F13: 0.9975 | G13: 0.852
A14: Byteful | B14: Singapore | C14: 20261025-0800 | D14: 2026-10-25 08:00:41 | E14: 1200 | F14: 0.995 | G14: 0.845
A15: Byteful | B15: Singapore | C15: 20261025-2000 | D15: 2026-10-25 20:00:02 | E15: 1200 | F15: 0.99916667 | G15: 0.849
... A267: SOAX | B267: USA (Ashburn) | C267: 20261027-2000 | D267: 2026-10-27 20:02:50 | E267: 1200 | F267: 0.99416667 | G267: 0.945

Sheet Method and limits
A1: Method and limitations (read before citing the numbers)
A3: Period: 2026-10-24 08:00 .. 2026-10-27 21:16 UTC. Three Hetzner Cloud servers: USA (Ashburn), Germany (Falkenstein), Singapore.
A4: 11 rotating pay-per-GB mobile proxy providers, 12 countries (US, DE, GB, FR, ES, BR, IN, PL, UA, TR, VN, ID).
A5: Not tested: Rayobyte (sales only, $250 minimum), Infatica (identity verification), Proxy-Cheap (phone and postal address required), Geonode and Webshare (no mobile proxies), Proxidize and Proxy-Seller (dedicated ports billed by time).
A6: Floppydata is the publisher and one of the tested providers; its traffic came from a package bought for the residential test. All scripts and raw data are published.
A7: Infrastructure: Cloudflare trace, new IP on every request, 30 s timeout, 5 parallel requests; failures count as results.
A8: Targets: Google search and the Instagram profile page as a phone browser without JavaScript. Success means the site let the IP in.
A9: Sticky: 30-minute sessions, one check every 30 s; IP lifetime ends at another IP or at 3 failed checks in a row.
A10: Fingerprint: p0f on our own endpoint; p0f reports Android as Linux and iOS as Mac OS X; carrier middleboxes can change TCP.
A11: IP quality: Scamalytics and IPinfo Lite on a sample of exit IPs; Mobile IP Share from IP2Location.io and MaxMind GeoIP2 Insights, shown side by side because the two databases disagree for some providers.
A12: Prices: regular price of the smallest package without promo codes or VAT, checked 23-26 Oct 2026; re-check before publication.
A13: Differences smaller than the width of the confidence intervals are not significant: overlapping intervals are a tie.
